pystrfry-1.0.3.data/scripts/strfry
strfry/__init__.py
pystrfry-1.0.3.dist-info/LICENSE
pystrfry-1.0.3.dist-info/METADATA
pystrfry-1.0.3.dist-info/WHEEL
pystrfry-1.0.3.dist-info/top_level.txt
pystrfry-1.0.3.dist-info/RECORD
