Metadata-Version: 2.1
Name: pystrfry
Version: 1.0.3
Summary: a tool for solving those annoying strfry CTF challenges
Home-page: UNKNOWN
Author: Aaron Esau
Author-email: redpwn@aaronesau.com
License: BSD-3-Clause
Platform: UNKNOWN
Requires-Python: >=3.6
